CHANGES.txt
LICENSE.txt
MANIFEST.in
README.txt
setup.cfg
setup.py
whtc/__init__.py
whtc.recipe.configmanager.egg-info/PKG-INFO
whtc.recipe.configmanager.egg-info/SOURCES.txt
whtc.recipe.configmanager.egg-info/dependency_links.txt
whtc.recipe.configmanager.egg-info/entry_points.txt
whtc.recipe.configmanager.egg-info/namespace_packages.txt
whtc.recipe.configmanager.egg-info/requires.txt
whtc.recipe.configmanager.egg-info/top_level.txt
whtc.recipe.configmanager.egg-info/zip-safe
whtc/recipe/__init__.py
whtc/recipe/configmanager/README.txt
whtc/recipe/configmanager/__init__.py
whtc/recipe/configmanager/tests.py
whtc/recipe/configmanager/testdata/MASTER_SECTION_FILE.TXT
whtc/recipe/configmanager/testdata/MASTER_TEST_FILE.INI
whtc/recipe/configmanager/testdata/TEMPLATE.IN