Metadata-Version: 1.1
Name: whtc.recipe.configmanager
Version: 1.1.3
Summary: A buildout recipe to manage auto-populating portions of shared configuration files that cannot simply be overwritten.
Home-page: http://pypi.python.org/pypi/whtc.recipe.configmanager
Author: Hugh T. Ranalli
Author-email: hugh@whtc.ca
License: UNKNOWN
Keywords: config configuration recipe buildout template
Platform: UNKNOWN
Classifier: Development Status :: 5 - Production/Stable
Classifier: Framework :: Buildout :: Recipe
Classifier: Intended Audience :: Developers
Classifier: Intended Audience :: System Administrators
Classifier: License :: OSI Approved :: GNU General Public License v3 (GPLv3)
Classifier: Programming Language :: Python
Classifier: Topic :: System :: Software Distribution
Classifier: Topic :: Software Development :: Libraries :: Python Modules
